[
  {
    "id": "KOERPER_001",
    "theme": "geometrie",
    "chapter": "koerper",
    "level": 1,
    "waveDuration": 3,
    "base": {
      "word": "Würfel",
      "type": "Körper",
      "visual": {
        "tier": 2,
        "size": 1,
        "appearance": "bold",
        "color": "#f39c12",
        "glow": true,
        "pulsate": true
      }
    },
    "correct": [
      {
        "entry": {
          "word": "6 Flächen",
          "type": "Eigenschaft"
        },
        "spawnPosition": 0.5,
        "spawnSpread": 0.05,
        "speed": 0.7,
        "points": 200,
        "pattern": "linear_inward",
        "hp": 1,
        "collectionOrder": 1,
        "context": "Ein Würfel hat 6 Flächen",
        "visual": {
          "color": "#e67e22",
          "variant": "hexagon",
          "pulsate": false,
          "fontSize": 1.1
        },
        "sound": "bubble_hit_soft"
      }
    ],
    "distractors": [
      {
        "entry": {
          "word": "4 Flächen",
          "type": "Wrong"
        },
        "spawnPosition": 0.3,
        "spawnSpread": 0.05,
        "speed": 0.9,
        "points": 100,
        "hp": 1,
        "damage": 1,
        "behavior": "seek_center",
        "context": "Ein Würfel hat nicht 4 Flächen",
        "visual": {
          "color": "#e74c3c",
          "variant": "diamond",
          "pulsate": true,
          "shake": false,
          "fontSize": 1
        },
        "sound": "explosion_minor"
      }
    ],
    "meta": {
      "source": "Mathe Geometrie",
      "tags": ["koerper", "level1"]
    }
  },
  {
    "id": "KOERPER_002",
    "theme": "geometrie",
    "chapter": "koerper",
    "level": 1,
    "waveDuration": 3,
    "base": {
      "word": "Quader",
      "type": "Körper",
      "visual": {
        "tier": 2,
        "size": 1,
        "appearance": "bold",
        "color": "#f39c12",
        "glow": true,
        "pulsate": true
      }
    },
    "correct": [
      {
        "entry": {
          "word": "6 Rechtecke",
          "type": "Eigenschaft"
        },
        "spawnPosition": 0.5,
        "spawnSpread": 0.05,
        "speed": 0.7,
        "points": 200,
        "pattern": "linear_inward",
        "hp": 1,
        "collectionOrder": 1,
        "context": "Ein Quader besteht aus 6 Rechtecken",
        "visual": {
          "color": "#e67e22",
          "variant": "hexagon",
          "pulsate": false,
          "fontSize": 1.1
        },
        "sound": "bubble_hit_soft"
      }
    ],
    "distractors": [
      {
        "entry": {
          "word": "4 Rechtecke",
          "type": "Wrong"
        },
        "spawnPosition": 0.3,
        "spawnSpread": 0.05,
        "speed": 0.9,
        "points": 100,
        "hp": 1,
        "damage": 1,
        "behavior": "seek_center",
        "context": "Ein Quader hat nicht 4 Rechtecke",
        "visual": {
          "color": "#e74c3c",
          "variant": "diamond",
          "pulsate": true,
          "shake": false,
          "fontSize": 1
        },
        "sound": "explosion_minor"
      }
    ],
    "meta": {
      "source": "Mathe Geometrie",
      "tags": ["koerper", "level1"]
    }
  },
  {
    "id": "KOERPER_003",
    "theme": "geometrie",
    "chapter": "koerper",
    "level": 1,
    "waveDuration": 3,
    "base": {
      "word": "Kugel",
      "type": "Körper",
      "visual": {
        "tier": 2,
        "size": 1,
        "appearance": "bold",
        "color": "#f39c12",
        "glow": true,
        "pulsate": true
      }
    },
    "correct": [
      {
        "entry": {
          "word": "keine Ecken",
          "type": "Eigenschaft"
        },
        "spawnPosition": 0.5,
        "spawnSpread": 0.05,
        "speed": 0.7,
        "points": 200,
        "pattern": "linear_inward",
        "hp": 1,
        "collectionOrder": 1,
        "context": "Eine Kugel hat keine Ecken",
        "visual": {
          "color": "#e67e22",
          "variant": "hexagon",
          "pulsate": false,
          "fontSize": 1.1
        },
        "sound": "bubble_hit_soft"
      }
    ],
    "distractors": [
      {
        "entry": {
          "word": "4 Ecken",
          "type": "Wrong"
        },
        "spawnPosition": 0.3,
        "spawnSpread": 0.05,
        "speed": 0.9,
        "points": 100,
        "hp": 1,
        "damage": 1,
        "behavior": "seek_center",
        "context": "Eine Kugel hat keine Ecken",
        "visual": {
          "color": "#e74c3c",
          "variant": "diamond",
          "pulsate": true,
          "shake": false,
          "fontSize": 1
        },
        "sound": "explosion_minor"
      }
    ],
    "meta": {
      "source": "Mathe Geometrie",
      "tags": ["koerper", "level1"]
    }
  },
  {
    "id": "KOERPER_004",
    "theme": "geometrie",
    "chapter": "koerper",
    "level": 1,
    "waveDuration": 3,
    "base": {
      "word": "Zylinder",
      "type": "Körper",
      "visual": {
        "tier": 2,
        "size": 1,
        "appearance": "bold",
        "color": "#f39c12",
        "glow": true,
        "pulsate": true
      }
    },
    "correct": [
      {
        "entry": {
          "word": "2 Kreise",
          "type": "Eigenschaft"
        },
        "spawnPosition": 0.5,
        "spawnSpread": 0.05,
        "speed": 0.7,
        "points": 200,
        "pattern": "linear_inward",
        "hp": 1,
        "collectionOrder": 1,
        "context": "Ein Zylinder hat 2 kreisförmige Grundflächen",
        "visual": {
          "color": "#e67e22",
          "variant": "hexagon",
          "pulsate": false,
          "fontSize": 1.1
        },
        "sound": "bubble_hit_soft"
      }
    ],
    "distractors": [
      {
        "entry": {
          "word": "1 Kreis",
          "type": "Wrong"
        },
        "spawnPosition": 0.3,
        "spawnSpread": 0.05,
        "speed": 0.9,
        "points": 100,
        "hp": 1,
        "damage": 1,
        "behavior": "seek_center",
        "context": "Ein Zylinder hat 2 Kreise, nicht 1",
        "visual": {
          "color": "#e74c3c",
          "variant": "diamond",
          "pulsate": true,
          "shake": false,
          "fontSize": 1
        },
        "sound": "explosion_minor"
      }
    ],
    "meta": {
      "source": "Mathe Geometrie",
      "tags": ["koerper", "level1"]
    }
  },
  {
    "id": "KOERPER_005",
    "theme": "geometrie",
    "chapter": "koerper",
    "level": 1,
    "waveDuration": 3,
    "base": {
      "word": "Pyramide",
      "type": "Körper",
      "visual": {
        "tier": 2,
        "size": 1,
        "appearance": "bold",
        "color": "#f39c12",
        "glow": true,
        "pulsate": true
      }
    },
    "correct": [
      {
        "entry": {
          "word": "spitze Form",
          "type": "Eigenschaft"
        },
        "spawnPosition": 0.5,
        "spawnSpread": 0.05,
        "speed": 0.7,
        "points": 200,
        "pattern": "linear_inward",
        "hp": 1,
        "collectionOrder": 1,
        "context": "Eine Pyramide hat eine spitze Form",
        "visual": {
          "color": "#e67e22",
          "variant": "hexagon",
          "pulsate": false,
          "fontSize": 1.1
        },
        "sound": "bubble_hit_soft"
      }
    ],
    "distractors": [
      {
        "entry": {
          "word": "runde Form",
          "type": "Wrong"
        },
        "spawnPosition": 0.3,
        "spawnSpread": 0.05,
        "speed": 0.9,
        "points": 100,
        "hp": 1,
        "damage": 1,
        "behavior": "seek_center",
        "context": "Eine Pyramide ist nicht rund",
        "visual": {
          "color": "#e74c3c",
          "variant": "diamond",
          "pulsate": true,
          "shake": false,
          "fontSize": 1
        },
        "sound": "explosion_minor"
      }
    ],
    "meta": {
      "source": "Mathe Geometrie",
      "tags": ["koerper", "level1"]
    }
  }
]

